array_subarray_utils/__init__.py
array_subarray_utils/subarray_utils.py
array_subarray_utils-0.1.0.dist-info/LICENSE
array_subarray_utils-0.1.0.dist-info/METADATA
array_subarray_utils-0.1.0.dist-info/WHEEL
array_subarray_utils-0.1.0.dist-info/top_level.txt
array_subarray_utils-0.1.0.dist-info/RECORD
