Metadata-Version: 2.1
Name: array_subarray_utils
Version: 0.1.0
Summary: A library for calculating subarray sums for arrays and circular arrays
Author: Ashiqur Rahman Sami
Author-email: samiashiqur@gmail.com
Classifier: Programming Language :: Python :: 3
Classifier: License :: OSI Approved :: MIT License
Classifier: Operating System :: OS Independent
Requires-Python: >=3.6
License-File: LICENSE
